flash_attention_triton/__init__.py
flash_attention_triton/_configurators_v2.py
flash_attention_triton/_triton_kernels_v2.py
flash_attention_triton/flash_attention_2.py
flash_attention_triton-0.1.0.dist-info/licenses/LICENSE
flash_attention_triton-0.1.0.dist-info/METADATA
flash_attention_triton-0.1.0.dist-info/WHEEL
flash_attention_triton-0.1.0.dist-info/top_level.txt
flash_attention_triton-0.1.0.dist-info/RECORD
