Metadata-Version: 2.4
Name: flash-attention-triton
Version: 0.1.0
Summary: Cross-platform FlashAttention-2 Triton implementation for Turing+ architectures
Author-email: Egor Zakharenko <egorzakharenko97@gmail.com>
License: MIT License
Project-URL: Homepage, https://github.com/egaoharu-kensei/flash-attention-triton
Project-URL: Repository, https://github.com/egaoharu-kensei/flash-attention-triton
Project-URL: Issue Tracker, https://github.com/egaoharu-kensei/flash-attention-triton/issues
Keywords: flash-attention,attention,transformers,triton,gpu,llm,optimization
Classifier: Development Status :: 4 - Beta
Classifier: Intended Audience :: Developers
Classifier: Intended Audience :: Science/Research
Classifier: License :: OSI Approved :: MIT License
Classifier: Operating System :: Microsoft :: Windows
Classifier: Operating System :: POSIX :: Linux
Classifier: Programming Language :: Python :: 3
Classifier: Topic :: Scientific/Engineering :: Artificial Intelligence
Requires-Python: >=3.10
License-File: LICENSE
Requires-Dist: packaging>=23.0
Provides-Extra: legacy
Requires-Dist: triton<=3.2.0,>=3.1.0; sys_platform == "linux" and extra == "legacy"
Requires-Dist: triton-windows<=3.2.0.post13,>=3.1.0.post17; sys_platform == "win32" and extra == "legacy"
Provides-Extra: modern
Requires-Dist: triton>=3.3.0; sys_platform == "linux" and extra == "modern"
Requires-Dist: triton-windows>=3.3.0.post19; sys_platform == "win32" and extra == "modern"
Provides-Extra: dev
Requires-Dist: mypy>=1.0.0; extra == "dev"
Requires-Dist: pre-commit>=3.0.0; extra == "dev"
Requires-Dist: pytest>=8.0.0; extra == "dev"
Requires-Dist: pytest-cov>=4.0.0; extra == "dev"
Requires-Dist: ruff>=0.7.0; extra == "dev"
Dynamic: license-file
